azure_functions_openapi/__init__.py
azure_functions_openapi/cache.py
azure_functions_openapi/cli.py
azure_functions_openapi/decorator.py
azure_functions_openapi/errors.py
azure_functions_openapi/monitoring.py
azure_functions_openapi/openapi.py
azure_functions_openapi/py.typed
azure_functions_openapi/server_info.py
azure_functions_openapi/swagger_ui.py
azure_functions_openapi/utils.py
azure_functions_openapi-0.8.0.dist-info/METADATA
azure_functions_openapi-0.8.0.dist-info/WHEEL
azure_functions_openapi-0.8.0.dist-info/entry_points.txt
azure_functions_openapi-0.8.0.dist-info/licenses/LICENSE
azure_functions_openapi-0.8.0.dist-info/RECORD
