Metadata-Version: 2.4
Name: azure-functions-openapi
Version: 0.8.0
Summary: OpenAPI (Swagger) integration for Python-based Azure Functions
Author-email: Yeongseon Choe <yeongseon.choe@gmail.com>
License-Expression: MIT
License-File: LICENSE
Requires-Python: <3.15,>=3.10
Requires-Dist: azure-functions
Requires-Dist: pydantic<3.0,>=1.10
Requires-Dist: pyyaml
Provides-Extra: dev
Requires-Dist: bandit==1.8.3; extra == 'dev'
Requires-Dist: black==25.1.0; extra == 'dev'
Requires-Dist: build; extra == 'dev'
Requires-Dist: coverage; extra == 'dev'
Requires-Dist: git-changelog; extra == 'dev'
Requires-Dist: hatch; extra == 'dev'
Requires-Dist: mypy==1.15.0; extra == 'dev'
Requires-Dist: pre-commit; extra == 'dev'
Requires-Dist: pytest; extra == 'dev'
Requires-Dist: pytest-cov; extra == 'dev'
Requires-Dist: ruff==0.11.13; extra == 'dev'
Requires-Dist: types-pyyaml; extra == 'dev'
Provides-Extra: docs
Requires-Dist: mkdocs; extra == 'docs'
Requires-Dist: mkdocs-material; extra == 'docs'
